pyaniparser/__init__.py
pyaniparser/parser.py
pyaniparser/types.py
pyaniparser/lib/Banned.AniParser.Native-windows-amd64.dll
pyaniparser-0.3.0.dist-info/METADATA
pyaniparser-0.3.0.dist-info/WHEEL
pyaniparser-0.3.0.dist-info/licenses/LICENSE
pyaniparser-0.3.0.dist-info/RECORD
