Metadata-Version: 2.4
Name: pyaniparser
Version: 0.3.0
Summary: Python wrapper for Banned.AniParser (NativeAOT C ABI)
License-File: LICENSE
Requires-Python: >=3.10
